epsearch/__init__.py
epsearch/_branching.py
epsearch/_cycle.py
epsearch/_diff_zeros.py
epsearch/py.typed
epsearch-1.0.0.dist-info/licenses/LICENSE
epsearch-1.0.0.dist-info/METADATA
epsearch-1.0.0.dist-info/WHEEL
epsearch-1.0.0.dist-info/top_level.txt
epsearch-1.0.0.dist-info/RECORD
