Metadata-Version: 2.4
Name: epsearch
Version: 1.0.0
Summary: Locate exceptional points of an analytic matrix
Author-email: ultrasphere-dev <34j.95a2p@simplelogin.com>
License-Expression: MIT
Project-URL: Bug Tracker, https://github.com/ultrasphere-dev/epsearch/issues
Project-URL: Changelog, https://github.com/ultrasphere-dev/epsearch/blob/main/CHANGELOG.md
Project-URL: documentation, https://epsearch.readthedocs.io
Project-URL: repository, https://github.com/ultrasphere-dev/epsearch
Classifier: Development Status :: 2 - Pre-Alpha
Classifier: Intended Audience :: Developers
Classifier: Natural Language :: English
Classifier: Operating System :: OS Independent
Classifier: Programming Language :: Python :: 3.10
Classifier: Programming Language :: Python :: 3.11
Classifier: Programming Language :: Python :: 3.12
Classifier: Programming Language :: Python :: 3.13
Classifier: Programming Language :: Python :: 3.14
Classifier: Topic :: Software Development :: Libraries
Requires-Python: >=3.10
License-File: LICENSE
Requires-Dist: attrs>=25.4.0
Requires-Dist: colormap-complex>=0.2.0
Requires-Dist: matplotlib-multicolored-line>=0.3.0
Requires-Dist: networkx>=3.4.2
Requires-Dist: seaborn>=0.13.2
Requires-Dist: ss-hankel>=1.0.0
Dynamic: license-file
